beaker_session_jwt.py
beaker_session_jwt-1.0.4.dist-info/METADATA
beaker_session_jwt-1.0.4.dist-info/WHEEL
beaker_session_jwt-1.0.4.dist-info/top_level.txt
beaker_session_jwt-1.0.4.dist-info/RECORD
