Metadata-Version: 2.4
Name: beaker-session-jwt
Version: 1.0.4
License-Expression: Apache-2.0
Project-URL: Homepage, https://github.com/brondsem/beaker-session-jwt
Project-URL: Changes, https://github.com/brondsem/beaker-session-jwt/blob/main/CHANGES.md
Classifier: Programming Language :: Python
Classifier: Programming Language :: Python :: 3.9
Classifier: Programming Language :: Python :: 3.10
Classifier: Programming Language :: Python :: 3.11
Classifier: Programming Language :: Python :: 3.12
Classifier: Programming Language :: Python :: 3.13
Classifier: Programming Language :: Python :: 3.14
Requires-Python: >=3.9
Requires-Dist: beaker<2
Requires-Dist: joserfc>=1.1.0
Requires-Dist: pymongo
Provides-Extra: test
Requires-Dist: webtest; extra == "test"
Requires-Dist: pytest; extra == "test"
